LICENSE
MANIFEST.in
README.md
setup.cfg
setup.py
ekankthian/__init__.py
ekankthian/config.py
ekankthian.egg-info/PKG-INFO
ekankthian.egg-info/SOURCES.txt
ekankthian.egg-info/dependency_links.txt
ekankthian.egg-info/requires.txt
ekankthian.egg-info/top_level.txt
ekankthian/Clients/__init__.py
ekankthian/Clients/client.py
ekankthian/Clients/pytgcalls.py
ekankthian/blacklist/__init__.py
ekankthian/blacklist/support.py
ekankthian/button/__init__.py
ekankthian/button/button.py
ekankthian/extra/__init__.py
ekankthian/extra/hosted.py
ekankthian/help/__init__.py
ekankthian/help/help.py
ekankthian/helper/__init__.py
ekankthian/helper/basic.py
ekankthian/helper/call.py
ekankthian/helper/data.py
ekankthian/helper/ekankth.py
ekankthian/helper/goblok.py
ekankthian/helper/hacking.py
ekankthian/helper/inline.py
ekankthian/helper/interval.py
ekankthian/helper/parser.py
ekankthian/helper/repo.py
ekankthian/helper/sticker.py
ekankthian/helper/tools.py
ekankthian/helper/utility.py
ekankthian/helper/what.py
ekankthian/methods/__init__.py
ekankthian/methods/queue.py
ekankthian/py_trans/__init__.py
ekankthian/py_trans/async_translator.py
ekankthian/py_trans/errors.py
ekankthian/py_trans/language_codes.py
ekankthian/py_trans/translator.py
ekankthian/pyrogram/__init__.py
ekankthian/pyrogram/_wrappers.py
ekankthian/pyrogram/func.py
ekankthian/pyrogram/misc.py
ekankthian/pyrogram/sections.py
ekankthian/pyrogram/toolbot.py
ekankthian/pyrogram/tools.py