Metadata-Version: 2.1
Name: ekankthian
Version: 0.1.15
Summary: BlackWeb Userbot 
Home-page: https://blackweb.tech
Author: Ekankth
Author-email: ekankth@gmail.com
License: MIT
Classifier: License :: OSI Approved :: MIT License
Classifier: Programming Language :: Python
Classifier: Programming Language :: Python :: 3
Classifier: Programming Language :: Python :: 3.6
Classifier: Programming Language :: Python :: 3.7
Classifier: Programming Language :: Python :: 3.8
Classifier: Programming Language :: Python :: Implementation :: CPython
Classifier: Programming Language :: Python :: Implementation :: PyPy
Requires-Python: ~=3.8
License-File: LICENSE
